odoo/addons/edi_account_oca/README.rst
odoo/addons/edi_account_oca/__init__.py
odoo/addons/edi_account_oca/__manifest__.py
odoo/addons/edi_account_oca/i18n/edi_account.pot
odoo/addons/edi_account_oca/i18n/edi_account_oca.pot
odoo/addons/edi_account_oca/i18n/es.po
odoo/addons/edi_account_oca/i18n/fr.po
odoo/addons/edi_account_oca/models/__init__.py
odoo/addons/edi_account_oca/models/account_move.py
odoo/addons/edi_account_oca/readme/CONTRIBUTORS.rst
odoo/addons/edi_account_oca/readme/DESCRIPTION.rst
odoo/addons/edi_account_oca/static/description/icon.png
odoo/addons/edi_account_oca/static/description/index.html
odoo/addons/edi_account_oca/tests/__init__.py
odoo/addons/edi_account_oca/tests/test_edi.py
odoo/addons/edi_account_oca/views/account_journal.xml
odoo/addons/edi_account_oca/views/account_move.xml
odoo/addons/edi_account_oca/views/edi_exchange_record.xml
odoo/addons/edi_account_oca/views/res_partner.xml
odoo14_addon_edi_account_oca-14.0.1.2.0.dist-info/METADATA
odoo14_addon_edi_account_oca-14.0.1.2.0.dist-info/WHEEL
odoo14_addon_edi_account_oca-14.0.1.2.0.dist-info/top_level.txt
odoo14_addon_edi_account_oca-14.0.1.2.0.dist-info/RECORD
